{"type":"PR","pr":{"number":937,"head":"dc1802a04eb951d209f42263e56d895f57e05958"},"user":"Kyle","status":"draft","branch":"cms/paul-issacs","collection":"authors","commitMessage":"Create Authors “paul-issacs”","title":"No Title","description":"No Description!","objects":{"entry":{"path":"_authors/paul-issacs.md","sha":"49a0045a751f42efe3593aac7149e0994074fe63"},"files":[{"path":"assets/images/content/paul-issacs.jpg","sha":"43fc870760b66fbf2823236db875f17d08d0adde"}]},"timeStamp":"2019-11-20T16:35:49.976Z"}